llama_index/tools/waii/__init__.py
llama_index/tools/waii/base.py
llama_index_tools_waii-0.4.1.dist-info/METADATA
llama_index_tools_waii-0.4.1.dist-info/WHEEL
llama_index_tools_waii-0.4.1.dist-info/licenses/LICENSE
llama_index_tools_waii-0.4.1.dist-info/RECORD
