Metadata-Version: 2.4
Name: llama-index-tools-waii
Version: 0.4.1
Summary: llama-index tools waii integration
Author-email: Your Name <you@example.com>
Maintainer: wangdatan
License-Expression: MIT
License-File: LICENSE
Requires-Python: <4.0,>=3.9
Requires-Dist: llama-index-core<0.15,>=0.13.0
Requires-Dist: waii-sdk-py<2,>=1.9.1
